{
  "headers": {
    "x-amz-version-id": "sObo73efYf0RiC2_rjs_5A2TGjqEL_36",
    "etag": "\"096147dfce9f649acd42f9abefff3e14\"",
    "x-amz-request-id": "2CD6SEX8N6CAXC64",
    "x-amz-id-2": "8GFb1rGZy67CGSsrC8LOFID+Z+lwWQwi3wgQvnUJD22IpfWrfyug0DnqHSxXTLM0e7Xb1axWy24=",
    "access-control-allow-origin": "*",
    "last-modified": "Sat, 18 Dec 2021 12:33:11 GMT",
    "server": "deploy/europe-west4-b",
    "content-length": "848",
    "cache-control": "public, max-age=31536000, immutable",
    "date": "Fri, 31 Dec 2021 19:54:14 GMT",
    "content-type": "application/typescript; charset=utf-8"
  },
  "url": "https://deno.land/x/mongo@v0.29.0/src/protocol/header.ts",
  "now": {
    "secs_since_epoch": 1640980453,
    "nanos_since_epoch": 960430000
  }
}